[
{"pagetitle":"赛事信息"},
{"type":"text", "value":""},
{"type":"title","value":"日程一览"},
{"type":"subtitle","value":"7月20日"},
{"type":"text", "value":"19:00前报到"},
{"type":"text", "value":"地点：山东省临沂市蒙山旅游区云蒙办事处百花峪村-天蒙山庄"},
{"type":"map","longitude":117.919640,"latitude": 35.562531,"markers":[{"id":"[117.919640, 35.562531]","title":"天蒙山庄","width":45,"height":45,"iconPath":"/image/marker.png","longitude":117.919640,"latitude": 35.562531}]},
{"type":"text", "value":"【点击地图中心地标可开启微信地图/导航/街景】"},
{"type":"text", "value":""},
{"type":"text", "value":"建议自驾，住宿天蒙山庄或附近山庄。"},
{"type":"text", "value":""},
{"type":"subtitle","value":"7月21日"},
{"type":"li", "value":"7:00 佛系爬刀山"},
{"type":"text", "value":"爬升/下降 490米"},
{"type":"text", "value":""},
{"type":"li", "value":"16:00—23:00 蒙山越野跑比赛"},
{"type":"text", "value":"线路：百花峪天蒙山庄-天蒙顶北山脊-百花峪-刀山北沟-上庄-大云蒙-凌云宫-刀山沟-百花峪天蒙山庄。、"},
{"type":"text", "value":"全程约19km，多为自然山径，累计爬升约1500米"},
{"type":"text", "value":""},
{"type":"subtitle","value":"7月22日"},
{"type":"li", "value":"6:00 刀山FKT精英表演赛"},
{"type":"text", "value":"刀山水库-刀山山脊-凌云宫-刀山沟-刀山水库。"},
{"type":"text", "value":"参赛自愿，需知悉活动危险性，并能在90分钟内完赛。"},
{"type":"li", "value":"9:00 曲流涧溯溪"},
{"type":"text", "value":""},
{"type":"title","value":"补给服务"},
{"type":"text", "value":"主办方将在起终点和补给站提供矿泉水等补给。"},
{"type":"text", "value":""},
{"type":"text", "value":"赛事将严格执行无纸杯化环保赛事。选手须用自带容器取水。所有选手及工作人员必须自带水杯或水袋。"},
{"type":"text", "value":""},
{"type":"title","value":"装备寄存服务"},
{"type":"text", "value":"赛事组委会将会在起终点为参赛选手提供装备寄存服务。"},
{"type":"text", "value":""},
{"type":"text", "value":"参赛选手须按照规定存放个人物品，贵重物品不得存放在包内（如手机、有效证件、现金、各式pad等），否则任何物品遗失由选手自行负责；"},
{"type":"text", "value":""},
{"type":"text", "value":"参赛选手可在比赛结束后到终点装备寄存区领取个人存放的物品。如超过领取时间没有领取的选手，组委会将按无人领取处理。"},
{"type":"text", "value":""},
{"type":"title","value":"强制装备"},
{"type":"text", "value":"每一位参赛选手必须全程穿着或携带所有赛会要求的强制装备，赛会将于赛前和赛中严格检查，出现任何一项不符合强制装备要求的情况，都将导致该选手直接被取消比赛资格。"}
]
