[{"pagetitle":"赛事信息"},{"type":"title","value":"大巴接驳安排"},{"type":"text","value":"2017年5月13日-周六"},{"type":"text","value":"路程：台州火车站（黄岩） -至- 沙埠太湖山庄"},{"type":"text","value":"班次：下午13:00; 15:00; 17:00; 19:00"},{"type":"text","value":""},{"type":"text","value":"2017年5月14日-周日"},{"type":"text","value":"路程：黄岩国际大酒店 -至- 沙埠太湖山庄"},{"type":"text","value":"班次：早上6:00 准时发车不候"},{"type":"text","value":""},{"type":"text","value":"2017年5月14日-周日"},{"type":"text","value":"路程：沙埠太湖山庄 -至- 台州火车站（黄岩)"},{"type":"text","value":"班次：早上6:00 准时发车不候"},{"type":"text","value":""},{"type":"title","value":"领物安排"},{"type":"text","value":"第一阶段：黄岩国际大酒店"},{"type":"text","value":"时间：5月12日 10:00-20:00"},{"type":"text","value":"     5月13日 10:00-13:00"},{"type":"text","value":""},{"type":"map","longitude":121.278277,"latitude":28.641244,"markers":[{"id":"[121.278277,28.641244]","title":"黄岩国际大酒店","width":30,"height":30,"iconPath":"/image/location.png","longitude":121.278277,"latitude":28.641244}]},{"type":"text","value":"\n"},{"type":"text","value":"\n"},{"type":"text","value":"第二阶段：沙埠太湖山庄度假酒店（起点）"},{"type":"text","value":"时间：5月13日 14:00-22:00"},{"type":"text","value":"     5月14日 06:30-07:30"},{"type":"text","value":""},{"type":"map","longitude":121.161239,"latitude":28.52324701,"markers":[{"id":"[121.161239,28.52324701]","title":"太湖山庄","width":30,"height":30,"iconPath":"/image/location.png","longitude":121.161239,"latitude":28.52324701}]},{"type":"title","value":"比赛日发枪时间"},{"type":"text","value":"32公里组：08:00am"},{"type":"text","value":"17公里组：08:15am"},{"type":"text","value":"\n"},{"type":"text","value":"\n"}]
