[
{"pagetitle":"赛事信息"},
{"type":"text", "value":""},
{"type":"title","value":"领物须知"},
{"type":"text", "value":""},
{"type":"text", "value":"地址：连云港花果山酒店 大堂"},
{"type":"text", "value":"时间：16日 15:00-18:00"},
{"type":"text", "value":"     17日 09:00-20:00"},
{"type":"map","longitude":119.237839,"latitude":34.655331,"markers":[{"id":"[119.237839,34.655331]","title":"","width":45,"height":45,"iconPath":"/image/marker.png","longitude":119.237839,"latitude":34.655331}]},
{"type":"text", "value":"【点击地图中心地标可开启微信地图/导航/街景】"},
{"type":"text", "value":""},
{"type":"text", "value":"领取装备时，须持有效身份证明（选手须持本人身份证原件，拒绝代领），并现场签署运动员责任告知书。"},
{"type":"text", "value":"50公里需提供完赛证明或体检证明任意一项纸质文件。"},
{"type":"text", "value":""},
{"type":"title","value":"比赛流程"},
{"type":"text", "value":""},
{"type":"image","value":"http://www.raceonhills.com/image/@raceid@/sc.png"},
{"type":"text", "value":""},
{"type":"title","value":"注意事项"},
{"type":"text", "value":""},
{"type":"li", "value":"选手由赛事组委会统一办理比赛期间的人身意外伤害保险。选手如有其他保险需求，可自行购买其他险种保险。"},
{"type":"li", "value":"因选手自身原因放弃名额或退赛，组委会不予退还报名费。"},
{"type":"li", "value":"涉及公路赛段，选手须在组委会划定的公路区域内进行比赛；乡村道路赛段须靠近路边进行比赛，过马路要注意来往车辆；景区内赛道须注意礼让来往游客。"},
{"type":"li", "value":"选手可根据需要拿取由主办方提供的食物及饮品，选手不能带走补给站内的水瓶、罐子或杯子，选手请自备盛水器具。"},
{"type":"li", "value":"选手在比赛中出现紧急情况急需救援时，请拔打组委会提供的救援电话，与救援人员取得联系。"},
{"type":"li", "value":"在较偏僻的地区，救援人员没有到达之前，需要救援的选手可用随身携带的简单医用品进行自救，披上救生毯，选择安全区域等候救援。"},
{"type":"text", "value":""},
{"type":"title","value":"环境保护"},
{"type":"li", "value":"赛道途径花果山景区为AAAAA级名胜风景区，原生态环境均为宝贵的自然资源遗产，保护自然环境人人有责，请选手切勿破坏自然环境。"},
{"type":"li", "value":"请选手们自觉遵守景区相关规定，文明参赛。"},
{"type":"li", "value":"赛事遵循零碳生态理念，请选手注意保护、不破坏赛道途径的原生态风貌。"},
{"type":"li", "value":"赛事响应“无痕山野”，选手要建立环保意识，在比赛过程中注意保护赛道途径的环境，请自带垃圾袋，不乱扔垃圾。"}
]
