[
{"pagetitle":"赛事信息"},
{"type":"text", "value":""},
{"type":"title","value":"领物须知"},
{"type":"text", "value":"时间：12月1日（周五）11:00-23:00"},
{"type":"text", "value":"地点：永泰县香米拉温泉酒店"},
{"type":"map","longitude":118.950538,"latitude":25.855160 ,"markers":[{"id":"[118.950538,25.855160 ]","title":"永泰县香米拉温泉酒店","width":45,"height":45,"iconPath":"/image/marker.png","longitude":118.950538,"latitude":25.855160 }]},
{"type":"text", "value":"【点击地图中心地标可开启微信地图/导航/街景】"},
{"type":"text", "value":""},
{"type":"text", "value":"参赛选手须凭有效身份证明原件领取参赛物品，号码布、计时芯片和赛事手环仅限本人领取。如果选手无法参赛，除号码布、计时芯片和赛事手环本以外的其他参赛物品，可由代领人持本人身份证原件和被代领人身份证复印件领取。"},
{"type":"text", "value":""},
{"type":"text", "value":""},
{"type":"text", "value":""},
{"type":"title","value":"技术说明会"},
{"type":"text", "value":"时间：19:00-21:00"},
{"type":"subtitle","value":"内容"},
{"type":"li", "value":"赛事技术说明会"},
{"type":"li", "value":"高黎贡山超级越野赛分享会"},
{"type":"li", "value":"《跑者的世界》新书发布会（睿行跑者出品）"},
{"type":"text", "value":""},
{"type":"title","value":"比赛流程"},
{"type":"text", "value":""},
{"type":"subtitle","value":"12月2日（周六）"},
{"type":"text", "value":"05:20 赛事接驳车发车"},
{"type":"text", "value":"乘车地点：永泰县香米拉温泉酒店"},
{"type":"text", "value":"06:20 检录开始"},
{"type":"text", "value":""},
{"type":"text", "value":"赛事起点：永泰赤壁温泉酒店"},
{"type":"map","longitude":119.084717,"latitude":25.855837 ,"markers":[{"id":"[119.084717,25.855837 ]","title":"永泰赤壁温泉酒店","width":45,"height":45,"iconPath":"/image/marker.png","longitude":119.084717,"latitude":25.855837 }]},
{"type":"text", "value":"【点击地图中心地标可开启微信地图/导航/街景】"},
{"type":"text", "value":""},
{"type":"text", "value":"07:00 赛事起跑"},
{"type":"text", "value":"14:30 半程组关门"},
{"type":"text", "value":"20:00 全程组关门"},
{"type":"text", "value":""},
{"type":"title","value":"接驳车安排"},
{"type":"subtitle","value":"起点接驳"},
{"type":"text", "value":"发车时间：05:20"},
{"type":"text", "value":"行车路线：香米拉温泉酒店—永泰乐峰赤壁景区（全、半程组起点）"},
{"type":"text", "value":"注意：请选手提前抵达香米拉温泉酒店登记乘车，接驳车将于05:20准点发车，逾期不候。"},
{"type":"text", "value":""},
{"type":"subtitle","value":"半程终点接驳"},
{"type":"text", "value":"发车时间：11:00-16:00，每隔40-50分钟/班；"},
{"type":"text", "value":"行车路线：永泰云顶景区（半程终点）—香米拉温泉酒店"},
{"type":"text", "value":""},
{"type":"subtitle","value":"全程终点接驳"},
{"type":"text", "value":"发车时间：14:00-20:30，每隔40-50分钟/班；"},
{"type":"text", "value":"行车路线：永泰乐峰赤壁景区（全程终点）—香米拉温泉酒店"}
]
